[
  {
    "id": 1,
    "title": "Web Design",
    "top_title": null,
    "content": "We’ve designed a culture that allows our stewards to assimilate",
    "url": "/services/web-design",
    "image": "ca441ed5-8928-49bc-bc08-94916df469d9",
    "highlight_colour": "#EE7102",
    "icon": "laptop_mac",
    "button_icon": "arrow_circle_right",
    "button_text": "Read more",
    "date": null,
    "tag": null,
    "type": "detailed",
    "block_grid_links": 1,
    "sort": 1,
    "author": null
  },
  {
    "id": 2,
    "title": "Web Development",
    "top_title": null,
    "content": "Unlock next-level digital experiences with Lewis Digital's web development services. Our team of experts leverages the latest technologies to develop websites that are not only aesthetically pleasing but also robust and secure, laying a solid foundation for your digital journey.",
    "url": "/services/web-development",
    "image": "a83fceac-93f4-47a5-b7e3-3cea81608cae",
    "highlight_colour": "#EE7102",
    "icon": "developer_mode",
    "button_icon": "arrow_circle_right",
    "button_text": "Read more",
    "date": null,
    "tag": null,
    "type": "detailed",
    "block_grid_links": 1,
    "sort": 2,
    "author": null
  },
  {
    "id": 3,
    "title": "E-commerce Websites",
    "top_title": null,
    "content": "Create a digital storefront that sells with Lewis Digital. We design and develop e-commerce websites that are user-friendly, secure, and built for success, offering seamless shopping experiences that turn visitors into loyal customers.",
    "url": "/services/e-commerce-websites",
    "image": "3689be19-81f9-4bc0-b43b-2e043a7072b2",
    "highlight_colour": "#EE7102",
    "icon": "shopping_cart",
    "button_icon": "arrow_circle_right",
    "button_text": "Read more",
    "date": null,
    "tag": null,
    "type": "detailed",
    "block_grid_links": 1,
    "sort": 4,
    "author": null
  },
  {
    "id": 4,
    "title": "SEO",
    "top_title": null,
    "content": "Boost your online visibility with Lewis Digital's SEO services. We craft tailored strategies to improve your website's ranking on search engines, driving organic traffic and fostering sustainable growth for your business.",
    "url": "/services/seo",
    "image": "ad1ff23b-2c46-4f24-85b6-49cac204ebb7",
    "highlight_colour": "#EE7102",
    "icon": "saved_search",
    "button_icon": "arrow_circle_right",
    "button_text": "Read more",
    "date": null,
    "tag": null,
    "type": "detailed",
    "block_grid_links": 1,
    "sort": 5,
    "author": null
  },
  {
    "id": 5,
    "title": "Branding",
    "top_title": null,
    "content": "Build a brand that echoes your business philosophy with Lewis Digital. Our branding solutions are tailored to resonate with your target audience, weaving a narrative that is compelling and consistent, fostering brand loyalty and recognition.",
    "url": "/services/branding",
    "image": "ca441ed5-8928-49bc-bc08-94916df469d9",
    "highlight_colour": "#EE7102",
    "icon": "design_services",
    "button_icon": "arrow_circle_right",
    "button_text": "Read more",
    "date": null,
    "tag": null,
    "type": "detailed",
    "block_grid_links": 1,
    "sort": 6,
    "author": null
  },
  {
    "id": 6,
    "title": "Apps & Web Apps",
    "top_title": null,
    "content": "Harness the power of cutting-edge web apps with Lewis Digital. We build dynamic, responsive, and highly functional web applications that streamline operations and foster business growth, adapting to your unique business requirements and goals.",
    "url": "/services/apps-web-apps",
    "image": "3689be19-81f9-4bc0-b43b-2e043a7072b2",
    "highlight_colour": null,
    "icon": "web",
    "button_icon": "arrow_circle_right",
    "button_text": "Read more",
    "date": null,
    "tag": null,
    "type": "detailed",
    "block_grid_links": 1,
    "sort": 3,
    "author": null
  },
  {
    "id": 7,
    "title": "Myers Financial",
    "top_title": null,
    "content": "Website and CMS build for Myers Financial",
    "url": "projects/myers-financial",
    "image": "3b2d7507-23cc-4105-ad68-2b2ea22cd465",
    "highlight_colour": "#EE7102",
    "icon": null,
    "button_icon": null,
    "button_text": null,
    "date": null,
    "tag": null,
    "type": "simple",
    "block_grid_links": 2,
    "sort": 1,
    "author": null
  },
  {
    "id": 8,
    "title": "Chemtrol",
    "top_title": null,
    "content": "A Web Server admin application re-design for a water treatment company",
    "url": "projects/chemtrol-admin",
    "image": "6c62645d-c518-43a0-80d7-a12cc2eca176",
    "highlight_colour": "#EE7102",
    "icon": null,
    "button_icon": null,
    "button_text": null,
    "date": null,
    "tag": null,
    "type": "simple",
    "block_grid_links": 2,
    "sort": 2,
    "author": null
  },
  {
    "id": 9,
    "title": "Team Spirit",
    "top_title": null,
    "content": "A sports coaching for Children bespoke website with CMS",
    "url": "projects/team-spirit",
    "image": "a83fceac-93f4-47a5-b7e3-3cea81608cae",
    "highlight_colour": "#EE7102",
    "icon": null,
    "button_icon": null,
    "button_text": null,
    "date": null,
    "tag": null,
    "type": "simple",
    "block_grid_links": 2,
    "sort": 3,
    "author": null
  },
  {
    "id": 10,
    "title": "Professional technology information & solutions are just like",
    "top_title": null,
    "content": null,
    "url": "blog/professional-technology",
    "image": "d47884fc-1fec-41ae-b7b6-de4c0183fc78",
    "highlight_colour": "#EE7102",
    "icon": null,
    "button_icon": "arrow_circle_right",
    "button_text": "Read more",
    "date": "2023-09-06",
    "tag": [
      {
        "name": "B Corp",
        "url": "url"
      },
      {
        "name": "Business",
        "url": "url"
      }
    ],
    "type": "article",
    "block_grid_links": 3,
    "sort": 1,
    "author": "Jacob Lewis"
  },
  {
    "id": 11,
    "title": "Blog article 2",
    "top_title": null,
    "content": null,
    "url": "blog",
    "image": "7c46832c-b0e4-4ced-9f67-cf2b8997aa1d",
    "highlight_colour": "#EE7102",
    "icon": null,
    "button_icon": "arrow_circle_right",
    "button_text": "Read more",
    "date": "2023-08-14",
    "tag": [
      {
        "name": "Business",
        "url": "url"
      },
      {
        "name": "Development",
        "url": "url"
      },
      {
        "name": "Sustainability",
        "url": "url"
      }
    ],
    "type": "article",
    "block_grid_links": 3,
    "sort": 2,
    "author": "Alexandra Lewis"
  },
  {
    "id": 12,
    "title": "This is another blog article",
    "top_title": null,
    "content": null,
    "url": "blog",
    "image": "ad1ff23b-2c46-4f24-85b6-49cac204ebb7",
    "highlight_colour": "#EE7102",
    "icon": null,
    "button_icon": "arrow_circle_right",
    "button_text": "Read more",
    "date": "2023-06-05",
    "tag": [
      {
        "name": "Design",
        "url": "url"
      }
    ],
    "type": "article",
    "block_grid_links": 3,
    "sort": 3,
    "author": "Jacob Lewis"
  }
]